warranted/__init__.py
warranted/crypto_helper.py
warranted/warranted_exception.py
warranted-1.0.0.dist-info/LICENSE
warranted-1.0.0.dist-info/METADATA
warranted-1.0.0.dist-info/WHEEL
warranted-1.0.0.dist-info/top_level.txt
warranted-1.0.0.dist-info/RECORD
