Metadata-Version: 2.1
Name: warranted
Version: 1.0.0
Summary: A Warranted helper library
Home-page: https://github.com/warranted-io/warranted-python
Author: API Team <api@warranted.io>
Author-email: api@warranted.io
License: MIT
Keywords: warranted api
Classifier: Development Status :: 5 - Production/Stable
Classifier: Intended Audience :: Developers
Classifier: License :: OSI Approved :: MIT License
Classifier: Programming Language :: Python :: 3
Classifier: Topic :: Software Development :: Libraries :: Python Modules
License-File: LICENSE
Requires-Dist: requests >=2.0.0
